ACKS.txt
CHANGES.txt
INSTALL.txt
LICENSE.txt
MANIFEST.in
README.md
pyproject.toml
setup.py
Durus.egg-info/PKG-INFO
Durus.egg-info/SOURCES.txt
Durus.egg-info/dependency_links.txt
Durus.egg-info/not-zip-safe
Durus.egg-info/top_level.txt
bin/db_renumber.py
bin/db_to_py3k.py
bin/durus
doc/CHANGES_CNRI.txt
doc/FAQ.txt
doc/LICENSE_CNRI.txt
doc/README_CNRI.txt
durus/__init__.py
durus/__main__.py
durus/_persistent.c
durus/btree.py
durus/client_storage.py
durus/connection.py
durus/error.py
durus/file.py
durus/file_storage.py
durus/file_storage2.py
durus/logger.py
durus/persistent.py
durus/persistent_dict.py
durus/persistent_list.py
durus/persistent_set.py
durus/serialize.py
durus/shelf.py
durus/sqlite_storage.py
durus/storage.py
durus/storage_server.py
durus/systemd_socket.py
durus/utils.py
test/__init__.py
test/stress.py
test/utest_btree.py
test/utest_client_storage.py
test/utest_connection.py
test/utest_file.py
test/utest_file_storage.py
test/utest_persistent.py
test/utest_persistent_dict.py
test/utest_persistent_list.py
test/utest_persistent_set.py
test/utest_serialize.py
test/utest_shelf.py
test/utest_storage.py
test/utest_storage_server.py
test/utest_utils.py