Metadata-Version: 1.0
Name: Durus
Version: 4.2
Summary: A Python Object Database
Home-page: https://github.com/nascheme/durus
Author: CNRI and others
Author-email: nas-durus@arctrix.com
License: see LICENSE.txt
Platform: Python >=2.6
